Workbook

Sheet Overview
A1: 365-Day AI Engineer Roadmap - 2 hours/day edition
A2: Day 1 = 07 Sep 2026 (Mon). Every day = 2 h: LEARN 45 min (read/watch the exact section listed) + IMPLEMENT/BUILD 75 min (code it) + 5 min revise. Day 7 = weekly checkpoint (grey, 2 h). Yellow = project checkpoint weeks. DSA is NOT in this plan - it uses its own time. Rule: if a day overruns, carry it to the next day and drop that week's lowest-value item; never skip the checkpoint.
A4: Week | B4: Days | C4: Phase | D4: Theme | E4: Difficulty | F4: Checkpoint | G4: Days done | H4: % done
A5: 1 | B5: 1-7 | C5: Phase 0 - Assessment & setup | D5: Assessment + engineering setup | E5: 2 | F5: CP0 | G5: =COUNTIF('365-Day Plan (2h)'!O2:O8,"Y") -> 0 | H5: =G5/7 -> 0
A6: 2 | B6: 8-14 | C6: Phase 1 - Mathematics | D6: Linear algebra I | E6: 3 | G6: =COUNTIF('365-Day Plan (2h)'!O9:O15,"Y") -> 0 | H6: =G6/7 -> 0
A7: 3 | B7: 15-21 | C7: Phase 1 - Mathematics | D7: Linear algebra II | E7: 4 | G7: =COUNTIF('365-Day Plan (2h)'!O16:O22,"Y") -> 0 | H7: =G7/7 -> 0
A8: 4 | B8: 22-28 | C8: Phase 1 - Mathematics | D8: Calculus & optimisation | E8: 4 | G8: =COUNTIF('365-Day Plan (2h)'!O23:O29,"Y") -> 0 | H8: =G8/7 -> 0
A9: 5 | B9: 29-35 | C9: Phase 1 - Mathematics | D9: Probability | E9: 3 | G9: =COUNTIF('365-Day Plan (2h)'!O30:O36,"Y") -> 0 | H9: =G9/7 -> 0
A10: 6 | B10: 36-42 | C10: Phase 1 - Mathematics | D10: Statistics | E10: 3 | F10: Math diagnostic v2 | G10: =COUNTIF('365-Day Plan (2h)'!O37:O43,"Y") -> 0 | H10: =G10/7 -> 0
A11: 7 | B11: 43-49 | C11: Phase 2 - Classical & advanced ML | D11: Regression, classification, metrics | E11: 3 | G11: =COUNTIF('365-Day Plan (2h)'!O44:O50,"Y") -> 0 | H11: =G11/7 -> 0
A12: 8 | B12: 50-56 | C12: Phase 2 - Classical & advanced ML | D12: Trees, forests, boosting | E12: 3 | G12: =COUNTIF('365-Day Plan (2h)'!O51:O57,"Y") -> 0 | H12: =G12/7 -> 0
A13: 9 | B13: 57-63 | C13: Phase 2 - Classical & advanced ML | D13: Unsupervised & anomaly | E13: 3 | G13: =COUNTIF('365-Day Plan (2h)'!O58:O64,"Y") -> 0 | H13: =G13/7 -> 0
A14: 10 | B14: 64-70 | C14: Phase 2 - Classical & advanced ML | D14: Advanced ML | E14: 4 | G14: =COUNTIF('365-Day Plan (2h)'!O65:O71,"Y") -> 0 | H14: =G14/7 -> 0
A15: 11 | B15: 71-77 | C15: Phase 2 - Classical & advanced ML | D15: PROJECT 1: PredictiveMaint-ML (week 1) | E15: 4 | G15: =COUNTIF('365-Day Plan (2h)'!O72:O78,"Y") -> 0 | H15: =G15/7 -> 0
A16: 12 | B16: 78-84 | C16: Phase 2 - Classical & advanced ML | D16: PROJECT 1 (week 2) | E16: 4 | F16: CP1 | G16: =COUNTIF('365-Day Plan (2h)'!O79:O85,"Y") -> 0 | H16: =G16/7 -> 0
A17: 13 | B17: 85-91 | C17: Phase 3 - Deep learning & PyTorch | D17: DL from scratch | E17: 4 | G17: =COUNTIF('365-Day Plan (2h)'!O86:O92,"Y") -> 0 | H17: =G17/7 -> 0
A18: 14 | B18: 92-98 | C18: Phase 3 - Deep learning & PyTorch | D18: PyTorch mastery | E18: 3 | G18: =COUNTIF('365-Day Plan (2h)'!O93:O99,"Y") -> 0 | H18: =G18/7 -> 0
A19: 15 | B19: 99-105 | C19: Phase 3 - Deep learning & PyTorch | D19: Training craft | E19: 4 | G19: =COUNTIF('365-Day Plan (2h)'!O100:O106,"Y") -> 0 | H19: =G19/7 -> 0
A20: 16 | B20: 106-112 | C20: Phase 3 - Deep learning & PyTorch | D20: CNNs | E20: 3 | G20: =COUNTIF('365-Day Plan (2h)'!O107:O113,"Y") -> 0 | H20: =G20/7 -> 0
A21: 17 | B21: 113-119 | C21: Phase 3 - Deep learning & PyTorch | D21: Sequence models | E21: 3 | G21: =COUNTIF('365-Day Plan (2h)'!O114:O120,"Y") -> 0 | H21: =G21/7 -> 0
A22: 18 | B22: 120-126 | C22: Phase 3 - Deep learning & PyTorch | D22: PROJECT 2: EdgeVibe-CNN (week 1) | E22: 4 | G22: =COUNTIF('365-Day Plan (2h)'!O121:O127,"Y") -> 0 | H22: =G22/7 -> 0
A23: 19 | B23: 127-133 | C23: Phase 3 - Deep learning & PyTorch | D23: PROJECT 2 (week 2) | E23: 4 | F23: CP2 | G23: =COUNTIF('365-Day Plan (2h)'!O128:O134,"Y") -> 0 | H23: =G23/7 -> 0
A24: 20 | B24: 134-140 | C24: Phase 4 - Transformers & LLMs | D24: Attention & transformer | E24: 4 | G24: =COUNTIF('365-Day Plan (2h)'!O135:O141,"Y") -> 0 | H24: =G24/7 -> 0
A25: 21 | B25: 141-147 | C25: Phase 4 - Transformers & LLMs | D25: Building GPT | E25: 4 | G25: =COUNTIF('365-Day Plan (2h)'!O142:O148,"Y") -> 0 | H25: =G25/7 -> 0
A26: 22 | B26: 148-154 | C26: Phase 4 - Transformers & LLMs | D26: Pretraining & inference | E26: 4 | G26: =COUNTIF('365-Day Plan (2h)'!O149:O155,"Y") -> 0 | H26: =G26/7 -> 0
A27: 23 | B27: 155-161 | C27: Phase 4 - Transformers & LLMs | D27: LLM systems | E27: 4 | G27: =COUNTIF('365-Day Plan (2h)'!O156:O162,"Y") -> 0 | H27: =G27/7 -> 0
A28: 24 | B28: 162-168 | C28: Phase 4 - Transformers & LLMs | D28: LLM behaviour & structured output | E28: 3 | G28: =COUNTIF('365-Day Plan (2h)'!O163:O169,"Y") -> 0 | H28: =G28/7 -> 0
A29: 25 | B29: 169-175 | C29: Phase 4 - Transformers & LLMs | D29: PROJECT 3: MiniGPT-Domain (week 1) | E29: 5 | G29: =COUNTIF('365-Day Plan (2h)'!O170:O176,"Y") -> 0 | H29: =G29/7 -> 0
A30: 26 | B30: 176-182 | C30: Phase 4 - Transformers & LLMs | D30: PROJECT 3 (week 2) | E30: 5 | F30: CP3 | G30: =COUNTIF('365-Day Plan (2h)'!O177:O183,"Y") -> 0 | H30: =G30/7 -> 0
A31: 27 | B31: 183-189 | C31: Phase 5 - Embeddings & RAG | D31: Embeddings & vector search | E31: 3 | G31: =COUNTIF('365-Day Plan (2h)'!O184:O190,"Y") -> 0 | H31: =G31/7 -> 0
A32: 28 | B32: 190-196 | C32: Phase 5 - Embeddings & RAG | D32: RAG Level 1-2 | E32: 3 | G32: =COUNTIF('365-Day Plan (2h)'!O191:O197,"Y") -> 0 | H32: =G32/7 -> 0
A33: 29 | B33: 197-203 | C33: Phase 5 - Embeddings & RAG | D33: RAG Level 3 | E33: 4 | G33: =COUNTIF('365-Day Plan (2h)'!O198:O204,"Y") -> 0 | H33: =G33/7 -> 0
A34: 30 | B34: 204-210 | C34: Phase 5 - Embeddings & RAG | D34: RAG Level 4: evaluation, cost, cache | E34: 4 | G34: =COUNTIF('365-Day Plan (2h)'!O205:O211,"Y") -> 0 | H34: =G34/7 -> 0
A35: 31 | B35: 211-217 | C35: Phase 5 - Embeddings & RAG | D35: PROJECT 4: RegRAG (week 1) | E35: 5 | G35: =COUNTIF('365-Day Plan (2h)'!O212:O218,"Y") -> 0 | H35: =G35/7 -> 0
A36: 32 | B36: 218-224 | C36: Phase 5 - Embeddings & RAG | D36: PROJECT 4 (week 2) | E36: 5 | F36: CP4 | G36: =COUNTIF('365-Day Plan (2h)'!O219:O225,"Y") -> 0 | H36: =G36/7 -> 0
A37: 33 | B37: 225-231 | C37: Phase 6 - Fine-tuning | D37: PEFT & quantisation | E37: 4 | G37: =COUNTIF('365-Day Plan (2h)'!O226:O232,"Y") -> 0 | H37: =G37/7 -> 0
A38: 34 | B38: 232-238 | C38: Phase 6 - Fine-tuning | D38: Instruction tuning, DPO, RAG-vs-FT | E38: 4 | G38: =COUNTIF('365-Day Plan (2h)'!O233:O239,"Y") -> 0 | H38: =G38/7 -> 0
A39: 35 | B39: 239-245 | C39: Phase 6 - Fine-tuning | D39: Whisper fine-tune on Tanglish | E39: 4 | G39: =COUNTIF('365-Day Plan (2h)'!O240:O246,"Y") -> 0 | H39: =G39/7 -> 0
A40: 36 | B40: 246-252 | C40: Phase 7 - Agents | D40: Agents I: loop & tools | E40: 3 | G40: =COUNTIF('365-Day Plan (2h)'!O247:O253,"Y") -> 0 | H40: =G40/7 -> 0
A41: 37 | B41: 253-259 | C41: Phase 7 - Agents | D41: Agents II: workflows vs agents | E41: 4 | G41: =COUNTIF('365-Day Plan (2h)'!O254:O260,"Y") -> 0 | H41: =G41/7 -> 0
A42: 38 | B42: 260-266 | C42: Phase 7 - Agents | D42: Agents III: framework week + security | E42: 4 | G42: =COUNTIF('365-Day Plan (2h)'!O261:O267,"Y") -> 0 | H42: =G42/7 -> 0
A43: 39 | B43: 267-273 | C43: Phase 7 - Agents | D43: PROJECT 5: TanglishVoice (week 1) | E43: 4 | G43: =COUNTIF('365-Day Plan (2h)'!O268:O274,"Y") -> 0 | H43: =G43/7 -> 0
A44: 40 | B44: 274-280 | C44: Phase 7 - Agents | D44: PROJECT 5 (week 2) | E44: 4 | F44: CP5 | G44: =COUNTIF('365-Day Plan (2h)'!O275:O281,"Y") -> 0 | H44: =G44/7 -> 0
A45: 41 | B45: 281-287 | C45: Phase 8 - Speech internals & edge | D45: ASR internals + TTS + VLM | E45: 4 | G45: =COUNTIF('365-Day Plan (2h)'!O282:O288,"Y") -> 0 | H45: =G45/7 -> 0
A46: 42 | B46: 288-294 | C46: Phase 8 - Speech internals & edge | D46: Edge AI | E46: 4 | G46: =COUNTIF('365-Day Plan (2h)'!O289:O295,"Y") -> 0 | H46: =G46/7 -> 0
A47: 43 | B47: 295-301 | C47: Phase 9 - MLOps, cloud, systems | D47: MLOps I: tracking, versioning, testing | E47: 3 | G47: =COUNTIF('365-Day Plan (2h)'!O296:O302,"Y") -> 0 | H47: =G47/7 -> 0
A48: 44 | B48: 302-308 | C48: Phase 9 - MLOps, cloud, systems | D48: MLOps II: serving, monitoring, drift | E48: 3 | G48: =COUNTIF('365-Day Plan (2h)'!O303:O309,"Y") -> 0 | H48: =G48/7 -> 0
A49: 45 | B49: 309-315 | C49: Phase 9 - MLOps, cloud, systems | D49: Azure | E49: 3 | G49: =COUNTIF('365-Day Plan (2h)'!O310:O316,"Y") -> 0 | H49: =G49/7 -> 0
A50: 46 | B50: 316-322 | C50: Phase 9 - MLOps, cloud, systems | D50: Distributed systems for AI + system design | E50: 4 | G50: =COUNTIF('365-Day Plan (2h)'!O317:O323,"Y") -> 0 | H50: =G50/7 -> 0
A51: 47 | B51: 323-329 | C51: Phase 9 - MLOps, cloud, systems | D51: PROJECT 6: platform (week 1) | E51: 5 | G51: =COUNTIF('365-Day Plan (2h)'!O324:O330,"Y") -> 0 | H51: =G51/7 -> 0
A52: 48 | B52: 330-336 | C52: Phase 9 - MLOps, cloud, systems | D52: PROJECT 6 (week 2) | E52: 5 | F52: CP6 | G52: =COUNTIF('365-Day Plan (2h)'!O331:O337,"Y") -> 0 | H52: =G52/7 -> 0
A53: 49 | B53: 337-343 | C53: Phase 10 - GPU & inference optimisation | D53: GPU basics & compression | E53: 4 | G53: =COUNTIF('365-Day Plan (2h)'!O338:O344,"Y") -> 0 | H53: =G53/7 -> 0
A54: 50 | B54: 344-350 | C54: Phase 10 - GPU & inference optimisation | D54: LLM serving | E54: 4 | G54: =COUNTIF('365-Day Plan (2h)'!O345:O351,"Y") -> 0 | H54: =G54/7 -> 0
A55: 51 | B55: 351-357 | C55: Phase 11 - Research engineering | D55: Reading, reproduction, ablation | E55: 4 | G55: =COUNTIF('365-Day Plan (2h)'!O352:O358,"Y") -> 0 | H55: =G55/7 -> 0
A56: 52 | B56: 358-364 | C56: Phase 12 - Flagship integration | D56: Flagship: Sentinel-Edge | E56: 5 | F56: CP7 | G56: =COUNTIF('365-Day Plan (2h)'!O359:O365,"Y") -> 0 | H56: =G56/7 -> 0
A57: Total | G57: =SUM(G5:G56)+COUNTIF('365-Day Plan (2h)'!O366:O366,"Y") -> 0 | H57: =G57/365 -> 0
A59: What was cut vs the 6-hour plan (to fit 730 hours):
A60: - Practice slots removed; exercises folded into the Implement block and the weekly checkpoint.
A61: - Project weeks doubled (2 weeks each) but with narrower scope; Project 6 is the lifecycle platform, flagship integration is 1 week.
A62: - Dropped: Triton, TensorRT deep dive, Kafka (concept only), VLM fine-tuning, video understanding, TTS fine-tuning, feature-store day, dedicated GPU-CUDA week (now 2 days), separate multimodal-RAG week (1 day).
A63: - Merged: ASR internals + TTS + VLM into one week; MLOps three weeks into two; distributed systems + system design into one week; research two weeks into one.
A64: - Kept intact: all mathematics, all from-scratch implementations (autodiff, GBM, LSTM, attention, GPT, BPE, KV cache, BM25, HNSW, LoRA, CTC), RAG L1-L4, fine-tuning, agents with security, Whisper fine-tune, edge deployment, MLflow/DVC/CI/Azure, vLLM benchmarks, one paper reproduction.
A65: If a phase finishes early, add the cut items back in this order: TensorRT -> Kafka -> VLM fine-tune -> Triton.

Sheet 365-Day Plan (2h)
A1: Day | B1: Date | C1: Week | D1: Phase | E1: Topic | F1: Concepts | G1: LEARN (45 min) - source & section | H1: Source key | I1: Source URL | J1: IMPLEMENT / BUILD (75 min) | K1: Revise (5 min) | L1: Deliverable | M1: Difficulty | N1: Checkpoint | O1: Done (Y/N)
A2: 1 | B2: 46272 | C2: 1 | D2: Phase 0 - Assessment & setup | E2: Environment + repo | F2: uv, pyproject, pytest, pre-commit, pyright | G2: PYDOCS: pytest fixtures; PROGIT ch 2 | H2: PYDOCS | I2: https://docs.python.org/3/library/asyncio.html | J2: Create `ai-lab` repo skeleton; one typed module + test; CI | K2: Yesterday: - | L2: Repo + CI green | M2: 2
A3: 2 | B3: 46273 | C3: 1 | D3: Phase 0 - Assessment & setup | E3: Math diagnostic | F3: LA/calc/prob/opt baseline | G3: None - closed-book test | H3: MML | I3: https://mml-book.github.io/ | J3: Take 20-Q diagnostic (MML chapter exercises); grade; weak list | K3: Yesterday: Environment + repo | L3: Score + weak topics | M3: 2
A4: 3 | B4: 46274 | C4: 1 | D4: Phase 0 - Assessment & setup | E4: PyTorch diagnostic | F4: Training loop, backprop | G4: None | H4: PT-TUT | I4: https://docs.pytorch.org/tutorials/ | J4: Blank-file MNIST training loop; derive 2-layer backprop on paper | K4: Yesterday: Math diagnostic | L4: Loop + derivation photo | M4: 2
A5: 4 | B5: 46275 | C5: 1 | D5: Phase 0 - Assessment & setup | E5: LLM/RAG diagnostic | F5: Attention, recall@k | G5: None | H5: OWN | I5: - | J5: Attention from memory; recall@5 on a past RAG corpus | K5: Yesterday: PyTorch diagnostic | L5: Two scripts + gap list | M5: 2
A6: 5 | B6: 46276 | C6: 1 | D6: Phase 0 - Assessment & setup | E6: Speech/agent/vector diagnostic | F6: WER, tool schemas, ANN | G6: JIWER README | H6: JIWER | I6: https://github.com/jitsi/jiwer | J6: WER on Tanglish clips; hackathon agent as plain loop; memory-engine vs FAISS | K6: Yesterday: LLM/RAG diagnostic | L6: WER table + benchmark | M6: 2
A7: 6 | B7: 46277 | C7: 1 | D7: Phase 0 - Assessment & setup | E7: Async + Docker + Git drills | F7: asyncio, retries, Dockerfile, rebase/bisect | G7: PYDOCS asyncio basics; DOCKER best practices | H7: PYDOCS | I7: https://docs.python.org/3/library/asyncio.html | J7: Async batch caller with rate limit; Dockerfile; rebase drill | K7: Yesterday: Speech/agent/vector diagnostic | L7: Container runs; CP0 self-grade | M7: 2
A8: 7 | B8: 46278 | C8: 1 | D8: Phase 0 - Assessment & setup | E8: WEEKLY CHECKPOINT 1: Assessment + engineering setup | F8: Whole week | G8: Anki + notes (30 min) | H8: OWN | I8: - | J8: Self-test 10 concept Qs + interview Qs: GIL vs asyncio for LLM calls; Why GPU runs aren't deterministic; What a Docker layer cache does (score bands: <40 weak, 40-60 needs work, 60-75 acceptable, 75-90 strong, 90+ excellent; <75% => revise before next week) (60 min); redo hardest implementation from blank file (30 min) | K8: Whole week | L8: Score + 200-word weekly note + push | M8: 2 | N8: CP0
A9: 8 | B9: 46279 | C9: 2 | D9: Phase 1 - Mathematics | E9: Vectors, span, systems | F9: Linear combinations, REF, Gaussian elimination | G9: MML 2.1-2.3; 3B1B-LA ep 1-3 | H9: MML | I9: https://mml-book.github.io/ | J9: Gaussian elimination from scratch; compare np.linalg.solve | K9: Yesterday: Async + Docker + Git drills | L9: `mathlib/linalg.py` + tests | M9: 3
A10: 9 | B10: 46280 | C10: 2 | D10: Phase 1 - Mathematics | E10: Vector spaces & independence | F10: Subspaces, independence test | G10: MML 2.4-2.5 | H10: MML | I10: https://mml-book.github.io/ | J10: Independence check via REF; 8 exercises | K10: Yesterday: Vectors, span, systems | L10: Commit | M10: 3
A11: 10 | B11: 46281 | C11: 2 | D11: Phase 1 - Mathematics | E11: Basis, rank, nullspace | F11: Rank-nullity, nullspace basis | G11: MML 2.6; 3B1B-LA ep 4-5 | H11: MML | I11: https://mml-book.github.io/ | J11: rank(), nullspace() | K11: Yesterday: Vector spaces & independence | L11: Commit + tests | M11: 3
A12: 11 | B12: 46282 | C12: 2 | D12: Phase 1 - Mathematics | E12: Linear mappings | F12: Matrix as map, image/kernel, composition | G12: MML 2.7; 3B1B-LA ep 6-8 | H12: MML | I12: https://mml-book.github.io/ | J12: Grid-transform visualiser | K12: Yesterday: Basis, rank, nullspace | L12: Plot + commit | M12: 3
A13: 12 | B13: 46283 | C13: 2 | D13: Phase 1 - Mathematics | E13: Change of basis, affine | F13: Basis change, affine maps | G13: MML 2.7.2-2.8; 3B1B-LA ep 12-13 | H13: MML | I13: https://mml-book.github.io/ | J13: Change-of-basis for rotation | K13: Yesterday: Linear mappings | L13: Commit | M13: 3
A14: 13 | B14: 46284 | C14: 2 | D14: Phase 1 - Mathematics | E14: Norms & inner products | F14: Lp norms, inner products, Cauchy-Schwarz | G14: MML 3.1-3.3 | H14: MML | I14: https://mml-book.github.io/ | J14: Norms; unit-ball plot; prove C-S once | K14: Yesterday: Change of basis, affine | L14: Commit + Anki 30 cards | M14: 3
A15: 14 | B15: 46285 | C15: 2 | D15: Phase 1 - Mathematics | E15: WEEKLY CHECKPOINT 2: Linear algebra I | F15: Whole week | G15: Anki + notes (30 min) | H15: OWN | I15: - | J15: Self-test 10 concept Qs + interview Qs: What rank tells you; When Ax=b has no/one/many solutions; Why matmul is composition (score bands: <40 weak, 40-60 needs work, 60-75 acceptable, 75-90 strong, 90+ excellent; <75% => revise before next week) (60 min); redo hardest implementation from blank file (30 min) | K15: Whole week | L15: Score + 200-word weekly note + push | M15: 3
A16: 15 | B16: 46286 | C16: 3 | D16: Phase 1 - Mathematics | E16: Angles, orthogonality, Gram-Schmidt | F16: Cosine similarity, orthonormal basis | G16: MML 3.4-3.5, 3.8; 3B1B-LA ep 9 | H16: MML | I16: https://mml-book.github.io/ | J16: cosine_similarity; Gram-Schmidt | K16: Yesterday: Norms & inner products | L16: Commit + tests | M16: 4
A17: 16 | B17: 46287 | C17: 3 | D17: Phase 1 - Mathematics | E17: Projections & least squares | F17: Projection matrix; least squares as projection | G17: MML 3.8 | H17: MML | I17: https://mml-book.github.io/ | J17: Least squares via projection vs lstsq; derive normal equations | K17: Yesterday: Angles, orthogonality, Gram-Schmidt | L17: Derivation + commit | M17: 4
A18: 17 | B18: 46288 | C18: 3 | D18: Phase 1 - Mathematics | E18: Determinant & eigen | F18: Volume scaling; characteristic polynomial; eigenspaces | G18: MML 4.1-4.2; 3B1B-LA ep 6, 14 | H18: MML | I18: https://mml-book.github.io/ | J18: det via elimination; power iteration; 2x2 by hand | K18: Yesterday: Projections & least squares | L18: Commit | M18: 4
A19: 18 | B19: 46289 | C19: 3 | D19: Phase 1 - Mathematics | E19: Eigendecomposition & Cholesky | F19: Spectral theorem; SPD | G19: MML 4.3-4.4 | H19: MML | I19: https://mml-book.github.io/ | J19: Symmetric eigendecomp; reconstruct A | K19: Yesterday: Determinant & eigen | L19: Commit + tests | M19: 4
A20: 19 | B20: 46290 | C20: 3 | D20: Phase 1 - Mathematics | E20: SVD | F20: U Sigma V^T; relation to A^T A; low rank | G20: MML 4.5-4.6 | H20: MML | I20: https://mml-book.github.io/ | J20: SVD via eigen(A^T A); image compression | K20: Yesterday: Eigendecomposition & Cholesky | L20: Plot + commit | M20: 4
... A42: 41 | B42: 46312 | C42: 6 | D42: Phase 1 - Mathematics | E42: Math diagnostic v2 | F42: All Phase 1 | G42: Anki review | H42: OWN | I42: - | J42: Retake 20-Q diagnostic; fix weak items | K42: Yesterday: A/B tests & drift tests | L42: Score >=75%; mathlib v1.0 | M42: 3
A43: 42 | B43: 46313 | C43: 6 | D43: Phase 1 - Mathematics | E43: WEEKLY CHECKPOINT 6: Statistics | F43: Whole week | G43: Anki + notes (30 min) | H43: OWN | I43: - | J43: Self-test 10 concept Qs + interview Qs: Bootstrap vs normal CI; What PSI measures; Compare two RAG configs statistically (score bands: <40 weak, 40-60 needs work, 60-75 acceptable, 75-90 strong, 90+ excellent; <75% => revise before next week) (60 min); redo hardest implementation from blank file (30 min) | K43: Whole week | L43: Score + 200-word weekly note + push | M43: 3 | N43: Math diagnostic v2
A44: 43 | B44: 46314 | C44: 7 | D44: Phase 2 - Classical & advanced ML | E44: Linear regression | F44: MSE, GD, normal equation, scaling | G44: NG C1 W1-2 | H44: NG | I44: https://www.coursera.org/specializations/machine-learning-introduction | J44: Linear regression from scratch vs sklearn | K44: Yesterday: Math diagnostic v2 | L44: `ml/linear.py` | M44: 3
A45: 44 | B45: 46315 | C45: 7 | D45: Phase 2 - Classical & advanced ML | E45: Logistic regression | F45: Sigmoid, log loss, boundary | G45: NG C1 W3 | H45: NG | I45: https://www.coursera.org/specializations/machine-learning-introduction | J45: Logistic from scratch | K45: Yesterday: Linear regression | L45: `ml/logistic.py` | M45: 3
A46: 45 | B46: 46316 | C46: 7 | D46: Phase 2 - Classical & advanced ML | E46: Regularisation & softmax | F46: L1/L2, early stopping, softmax regression | G46: NG C1 W3; GERON ch 4 | H46: GERON | I46: https://github.com/ageron/handson-ml3 | J46: Ridge/lasso paths; softmax on Iris | K46: Yesterday: Logistic regression | L46: Commit | M46: 3
A47: 46 | B47: 46317 | C47: 7 | D47: Phase 2 - Classical & advanced ML | E47: Classification metrics | F47: Confusion, P/R/F1, PR vs ROC, thresholds | G47: GERON ch 3 | H47: GERON | I47: https://github.com/ageron/handson-ml3 | J47: Metrics from scratch; curves | K47: Yesterday: Regularisation & softmax | L47: `ml/metrics.py` | M47: 3
A48: 47 | B48: 46318 | C48: 7 | D48: Phase 2 - Classical & advanced ML | E48: Calibration & cost | F48: Reliability diagrams, isotonic, expected cost | G48: GERON ch 3 + sklearn calibration docs | H48: GERON | I48: https://github.com/ageron/handson-ml3 | J48: Calibration curve; cost-based threshold | K48: Yesterday: Classification metrics | L48: Commit | M48: 3
A49: 48 | B49: 46319 | C49: 7 | D49: Phase 2 - Classical & advanced ML | E49: kNN & curse of dimensionality | F49: kNN; distances; link to ANN | G49: GERON ch 2 (kNN) + OWN | H49: OWN | I49: - | J49: kNN from scratch; dimensionality experiment | K49: Yesterday: Calibration & cost | L49: `ml/knn.py` + Anki | M49: 3
A50: 49 | B50: 46320 | C50: 7 | D50: Phase 2 - Classical & advanced ML | E50: WEEKLY CHECKPOINT 7: Regression, classification, metrics | F50: Whole week | G50: Anki + notes (30 min) | H50: OWN | I50: - | J50: Self-test 10 concept Qs + interview Qs: PR-AUC vs ROC-AUC; Why calibrate GBMs; kNN in high dimensions (score bands: <40 weak, 40-60 needs work, 60-75 acceptable, 75-90 strong, 90+ excellent; <75% => revise before next week) (60 min); redo hardest implementation from blank file (30 min) | K50: Whole week | L50: Score + 200-word weekly note + push | M50: 3
A51: 50 | B51: 46321 | C51: 8 | D51: Phase 2 - Classical & advanced ML | E51: Decision trees | F51: Entropy/Gini, CART, pruning | G51: GERON ch 6; NG C2 W4 | H51: GERON | I51: https://github.com/ageron/handson-ml3 | J51: CART from scratch | K51: Yesterday: kNN & curse of dimensionality | L51: `ml/tree.py` | M51: 3
A52: 51 | B52: 46322 | C52: 8 | D52: Phase 2 - Classical & advanced ML | E52: Random forests | F52: Bootstrap, feature subsampling, OOB | G52: GERON ch 7 | H52: GERON | I52: https://github.com/ageron/handson-ml3 | J52: RF from your tree | K52: Yesterday: Decision trees | L52: Commit | M52: 3
A53: 52 | B53: 46323 | C53: 8 | D53: Phase 2 - Classical & advanced ML | E53: Gradient boosting | F53: Residual fitting, shrinkage, early stopping | G53: GERON ch 7; XGBoost paper sec 2 (arxiv 1603.02754) | H53: GERON | I53: https://github.com/ageron/handson-ml3 | J53: Own GBM (regression + logistic) | K53: Yesterday: Random forests | L53: `ml/gbm.py` | M53: 3
A54: 53 | B54: 46324 | C54: 8 | D54: Phase 2 - Classical & advanced ML | E54: LightGBM/CatBoost in practice | F54: Histogram, leaf-wise, ordered boosting; key params | G54: LGBM tuning page | H54: LGBM | I54: https://lightgbm.readthedocs.io/en/latest/Parameters-Tuning.html | J54: Tune 5 params on AI4I; compare libs | K54: Yesterday: Gradient boosting | L54: Table | M54: 3
A55: 54 | B55: 46325 | C55: 8 | D55: Phase 2 - Classical & advanced ML | E55: SHAP | F55: Shapley values, TreeSHAP, PDP | G55: SHAP intro | H55: SHAP | I55: https://shap.readthedocs.io/ | J55: SHAP on GBM | K55: Yesterday: LightGBM/CatBoost in practice | L55: Plots | M55: 3
... A84: 83 | B84: 46354 | C84: 12 | D84: Phase 2 - Classical & advanced ML | E84: P1 defence | F84: 9 project questions | G84: Project/build day - no new reading | H84: OWN | I84: - | J84: Answer in writing; 5-min recorded explanation | K84: Yesterday: P1 API stub | L84: CP1 self-grade | M84: 4
A85: 84 | B85: 46355 | C85: 12 | D85: Phase 2 - Classical & advanced ML | E85: WEEKLY CHECKPOINT 12: PROJECT 1 (week 2) | F85: Whole week | G85: Anki + notes (30 min) | H85: OWN | I85: - | J85: Self-test 10 concept Qs + interview Qs: What leaked and how found; What you'd change in V2; Cost-curve interpretation (score bands: <40 weak, 40-60 needs work, 60-75 acceptable, 75-90 strong, 90+ excellent; <75% => revise before next week) (60 min); redo hardest implementation from blank file (30 min) | K85: Whole week | L85: Score + 200-word weekly note + push | M85: 4 | N85: CP1
A86: 85 | B86: 46356 | C86: 13 | D86: Phase 3 - Deep learning & PyTorch | E86: micrograd I | F86: Derivatives, graph, forward | G86: KZ micrograd (first half) | H86: KZ | I86: https://karpathy.ai/zero-to-hero.html | J86: Value class + forward | K86: Yesterday: P1 defence | L86: Commit | M86: 4
A87: 86 | B87: 46357 | C87: 13 | D87: Phase 3 - Deep learning & PyTorch | E87: micrograd II | F87: Backward, topological sort, MLP, training loop | G87: KZ micrograd (second half) | H87: KZ | I87: https://karpathy.ai/zero-to-hero.html | J87: backward() + MLP; gradient check | K87: Yesterday: micrograd I | L87: Gradcheck <1e-5 | M87: 4
A88: 87 | B88: 46358 | C88: 13 | D88: Phase 3 - Deep learning & PyTorch | E88: makemore 1 | F88: Bigram, NLL, one-layer NN | G88: KZ makemore 1 | H88: KZ | I88: https://karpathy.ai/zero-to-hero.html | J88: Bigram LM (counts + NN) | K88: Yesterday: micrograd II | L88: Commit | M88: 4
A89: 88 | B89: 46359 | C89: 13 | D89: Phase 3 - Deep learning & PyTorch | E89: makemore 2 | F89: Embeddings, context, mini-batch, LR sweep | G89: KZ makemore 2 | H89: KZ | I89: https://karpathy.ai/zero-to-hero.html | J89: MLP LM; LR sweep plot | K89: Yesterday: makemore 1 | L89: Commit | M89: 4
A90: 89 | B90: 46360 | C90: 13 | D90: Phase 3 - Deep learning & PyTorch | E90: makemore 3 | F90: Init, saturation, batchnorm | G90: KZ makemore 3 | H90: KZ | I90: https://karpathy.ai/zero-to-hero.html | J90: BatchNorm1d from scratch; stats plots | K90: Yesterday: makemore 2 | L90: Commit | M90: 4
A91: 90 | B91: 46361 | C91: 13 | D91: Phase 3 - Deep learning & PyTorch | E91: makemore 4 | F91: Manual backprop through CE/linear/tanh/BN | G91: KZ makemore 4 | H91: KZ | I91: https://karpathy.ai/zero-to-hero.html | J91: Manual gradients match PyTorch | K91: Yesterday: makemore 3 | L91: allclose passes + Anki | M91: 4
A92: 91 | B92: 46362 | C92: 13 | D92: Phase 3 - Deep learning & PyTorch | E92: WEEKLY CHECKPOINT 13: DL from scratch | F92: Whole week | G92: Anki + notes (30 min) | H92: OWN | I92: - | J92: Self-test 10 concept Qs + interview Qs: Why Kaiming init; BatchNorm at test time; Backprop of softmax-CE (score bands: <40 weak, 40-60 needs work, 60-75 acceptable, 75-90 strong, 90+ excellent; <75% => revise before next week) (60 min); redo hardest implementation from blank file (30 min) | K92: Whole week | L92: Score + 200-word weekly note + push | M92: 4
A93: 92 | B93: 46363 | C93: 14 | D93: Phase 3 - Deep learning & PyTorch | E93: Tensors & autograd | F93: Views, broadcasting, autograd graph, detach | G93: PT-TUT Basics + Autograd | H93: PT-TUT | I93: https://docs.pytorch.org/tutorials/ | J93: Autograd experiments; custom autograd.Function | K93: Yesterday: makemore 4 | L93: Commit | M93: 3
A94: 93 | B94: 46364 | C94: 14 | D94: Phase 3 - Deep learning & PyTorch | E94: Dataset/DataLoader/nn.Module | F94: Custom datasets, collate, workers | G94: PT-TUT Data | H94: PT-TUT | I94: https://docs.pytorch.org/tutorials/ | J94: Dataset for vibration windows; Module | K94: Yesterday: Tensors & autograd | L94: Commit + tests | M94: 3
A95: 94 | B95: 46365 | C95: 14 | D95: Phase 3 - Deep learning & PyTorch | E95: Training loop from memory | F95: Optimizers, schedulers, clipping, eval mode | G95: PT-TUT Optimization | H95: PT-TUT | I95: https://docs.pytorch.org/tutorials/ | J95: Blank-file loop with config/seed/logging (timed) | K95: Yesterday: Dataset/DataLoader/nn.Module | L95: <20 min from memory | M95: 3
A96: 95 | B96: 46366 | C96: 14 | D96: Phase 3 - Deep learning & PyTorch | E96: AMP + checkpoints | F96: autocast, GradScaler, resume | G96: PT-AMP; PT-TUT Save/Load | H96: PT-AMP | I96: https://docs.pytorch.org/tutorials/recipes/recipes/amp_recipe.html | J96: AMP loop on 3060; VRAM vs batch; resume | K96: Yesterday: Training loop from memory | L96: Table | M96: 3
A97: 96 | B97: 46367 | C97: 14 | D97: Phase 3 - Deep learning & PyTorch | E97: Profiling | F97: torch.profiler; data-loading bottlenecks | G97: PT-PROF | H97: PT-PROF | I97: https://docs.pytorch.org/tutorials/recipes/recipes/profiler_recipe.html | J97: Profile; fix top bottleneck | K97: Yesterday: AMP + checkpoints | L97: Report | M97: 3
... A133: 132 | B133: 46403 | C133: 19 | D133: Phase 3 - Deep learning & PyTorch | E133: P2 defence | F133: 9 questions + video | G133: Project/build day - no new reading | H133: OWN | I133: - | J133: Written answers + 3-min video | K133: Yesterday: P2 reproduce | L133: CP2 self-grade | M133: 4
A134: 133 | B134: 46404 | C134: 19 | D134: Phase 3 - Deep learning & PyTorch | E134: WEEKLY CHECKPOINT 19: PROJECT 2 (week 2) | F134: Whole week | G134: Anki + notes (30 min) | H134: OWN | I134: - | J134: Self-test 10 concept Qs + interview Qs: How you measured latency honestly; Why spectrogram+CNN; What breaks on ARM (score bands: <40 weak, 40-60 needs work, 60-75 acceptable, 75-90 strong, 90+ excellent; <75% => revise before next week) (60 min); redo hardest implementation from blank file (30 min) | K134: Whole week | L134: Score + 200-word weekly note + push | M134: 4 | N134: CP2
A135: 134 | B135: 46405 | C135: 20 | D135: Phase 4 - Transformers & LLMs | E135: Self-attention trick | F135: Averaging via matmul, masking | G135: KZ 'Let's build GPT' 0:00-1:00; RASCHKA 3.1-3.3 | H135: KZ | I135: https://karpathy.ai/zero-to-hero.html | J135: Weighted aggregation; simple attention | K135: Yesterday: P2 defence | L135: Commit | M135: 4
A136: 135 | B136: 46406 | C136: 20 | D136: Phase 4 - Transformers & LLMs | E136: Scaled dot-product, causal | F136: Q/K/V, sqrt(d_k), mask | G136: RASCHKA 3.4-3.5; AIAYN 3.2 | H136: RASCHKA | I136: https://github.com/rasbt/LLMs-from-scratch | J136: CausalAttention + mask tests | K136: Yesterday: Self-attention trick | L136: Commit + tests | M136: 4
A137: 136 | B137: 46407 | C137: 20 | D137: Phase 4 - Transformers & LLMs | E137: Multi-head attention | F137: Weight-split heads, projection | G137: RASCHKA 3.6; AIAYN 3.2.2 | H137: RASCHKA | I137: https://github.com/rasbt/LLMs-from-scratch | J137: MHA vs nn.MultiheadAttention | K137: Yesterday: Scaled dot-product, causal | L137: Commit | M137: 4
A138: 137 | B138: 46408 | C138: 20 | D138: Phase 4 - Transformers & LLMs | E138: Positional encodings | F138: Sinusoidal, learned, RoPE | G138: AIAYN 3.5; ROPE sec 3 | H138: ROPE | I138: https://arxiv.org/abs/2104.09864 | J138: Sinusoidal + RoPE implementation | K138: Yesterday: Multi-head attention | L138: Commit + tests | M138: 4
A139: 138 | B139: 46409 | C139: 20 | D139: Phase 4 - Transformers & LLMs | E139: Block: LN, residuals, FFN, GELU | F139: Pre-LN vs post-LN | G139: RASCHKA 4.1-4.5 | H139: RASCHKA | I139: https://github.com/rasbt/LLMs-from-scratch | J139: Transformer block; gradient-flow test | K139: Yesterday: Positional encodings | L139: Commit | M139: 4
A140: 139 | B140: 46410 | C140: 20 | D140: Phase 4 - Transformers & LLMs | E140: Encoder-decoder & masks | F140: Cross-attention, padding masks | G140: AIAYN sec 3; RASCHKA ch 1 | H140: AIAYN | I140: https://arxiv.org/abs/1706.03762 | J140: Tiny encoder-decoder (toy) | K140: Yesterday: Block: LN, residuals, FFN, GELU | L140: Commit + Anki | M140: 4
A141: 140 | B141: 46411 | C141: 20 | D141: Phase 4 - Transformers & LLMs | E141: WEEKLY CHECKPOINT 20: Attention & transformer | F141: Whole week | G141: Anki + notes (30 min) | H141: OWN | I141: - | J141: Self-test 10 concept Qs + interview Qs: Why sqrt(d_k); Pre-LN vs post-LN; RoPE vs learned (score bands: <40 weak, 40-60 needs work, 60-75 acceptable, 75-90 strong, 90+ excellent; <75% => revise before next week) (60 min); redo hardest implementation from blank file (30 min) | K141: Whole week | L141: Score + 200-word weekly note + push | M141: 4
A142: 141 | B142: 46412 | C142: 21 | D142: Phase 4 - Transformers & LLMs | E142: BPE tokenizer | F142: Merges, special tokens | G142: RASCHKA 2.1-2.5; KZ tokenizer video | H142: KZ | I142: https://karpathy.ai/zero-to-hero.html | J142: Own BPE trainer; compare tiktoken | K142: Yesterday: Encoder-decoder & masks | L142: `bpe.py` + tests | M142: 4
A143: 142 | B143: 46413 | C143: 21 | D143: Phase 4 - Transformers & LLMs | E143: Data loading & embeddings | F143: Sliding window; token+pos embeddings | G143: RASCHKA 2.6-2.8 | H143: RASCHKA | I143: https://github.com/rasbt/LLMs-from-scratch | J143: GPTDataset + loader | K143: Yesterday: BPE tokenizer | L143: Commit | M143: 4
A144: 143 | B144: 46414 | C144: 21 | D144: Phase 4 - Transformers & LLMs | E144: Full GPT | F144: Config, stacking, head, params | G144: RASCHKA 4.6-4.7 | H144: RASCHKA | I144: https://github.com/rasbt/LLMs-from-scratch | J144: GPTModel (124M); greedy generate | K144: Yesterday: Data loading & embeddings | L144: Commit | M144: 4
A145: 144 | B145: 46415 | C145: 21 | D145: Phase 4 - Transformers & LLMs | E145: Load GPT-2 weights | F145: Weight mapping; verification | G145: RASCHKA 5.5 | H145: RASCHKA | I145: https://github.com/rasbt/LLMs-from-scratch | J145: Load OpenAI GPT-2; logit diff vs HF | K145: Yesterday: Full GPT | L145: Diff <1e-3 | M145: 4
A146: 145 | B146: 46416 | C146: 21 | D146: Phase 4 - Transformers & LLMs | E146: Modern arch: RMSNorm/SwiGLU/RoPE/GQA | F146: LLaMA-style components | G146: CS336 lecture 3; LLaMA paper sec 2 (arxiv 2302.13971) | H146: CS336 | I146: https://stanford-cs336.github.io/ | J146: Variant model | K146: Yesterday: Load GPT-2 weights | L146: Commit + tests | M146: 4
... A182: 181 | B182: 46452 | C182: 26 | D182: Phase 4 - Transformers & LLMs | E182: P3 defence + blog | F182: 9 questions; write-up | G182: Project/build day - no new reading | H182: OWN | I182: - | J182: Answers + post | K182: Yesterday: P3 reproduce | L182: CP3 self-grade | M182: 5
A183: 182 | B183: 46453 | C183: 26 | D183: Phase 4 - Transformers & LLMs | E183: WEEKLY CHECKPOINT 26: PROJECT 3 (week 2) | F183: Whole week | G183: Anki + notes (30 min) | H183: OWN | I183: - | J183: Self-test 10 concept Qs + interview Qs: What changes at 1B params; Pre-LN reasoning; Your scaling result (score bands: <40 weak, 40-60 needs work, 60-75 acceptable, 75-90 strong, 90+ excellent; <75% => revise before next week) (60 min); redo hardest implementation from blank file (30 min) | K183: Whole week | L183: Score + 200-word weekly note + push | M183: 5 | N183: CP3
A184: 183 | B184: 46454 | C184: 27 | D184: Phase 5 - Embeddings & RAG | E184: Embedding models | F184: Contrastive training; pooling; MTEB | G184: SBERT docs | H184: SBERT | I184: https://www.sbert.net/ | J184: Compare 2 models on your corpus; tiny contrastive train | K184: Yesterday: P3 defence + blog | L184: Table | M184: 3
A185: 184 | B185: 46455 | C185: 27 | D185: Phase 5 - Embeddings & RAG | E185: Similarity & brute force | F185: Cosine/dot/L2; batched search | G185: Project/build day - no new reading | H185: OWN | I185: - | J185: Brute-force GPU store | K185: Yesterday: Embedding models | L185: Commit | M185: 3
A186: 185 | B186: 46456 | C186: 27 | D186: Phase 5 - Embeddings & RAG | E186: HNSW (your engine) | F186: Layers, ef/M, heuristic | G186: HNSW sec 1-4 | H186: HNSW | I186: https://arxiv.org/abs/1603.09320 | J186: Verify/finish HNSW; sweep | K186: Yesterday: Similarity & brute force | L186: Recall/QPS chart | M186: 3
A187: 186 | B187: 46457 | C187: 27 | D187: Phase 5 - Embeddings & RAG | E187: IVF/PQ & FAISS | F187: Inverted files; product quantisation | G187: FAISS wiki index guidelines | H187: FAISS | I187: https://github.com/facebookresearch/faiss/wiki | J187: IVF-PQ vs HNSW vs brute | K187: Yesterday: HNSW (your engine) | L187: Table | M187: 3
A188: 187 | B188: 46458 | C188: 27 | D188: Phase 5 - Embeddings & RAG | E188: pgvector | F188: HNSW in Postgres; filtering; hybrid with tsvector | G188: PGVECTOR README | H188: PGVECTOR | I188: https://github.com/pgvector/pgvector | J188: Postgres store with metadata filters | K188: Yesterday: IVF/PQ & FAISS | L188: Commit + tests | M188: 3
A189: 188 | B189: 46459 | C189: 27 | D189: Phase 5 - Embeddings & RAG | E189: Late interaction (concept) | F189: ColBERT, learned sparse | G189: SPLADE (ColBERT) sec 3 skim | H189: SPLADE | I189: https://arxiv.org/abs/2004.12832 | J189: Notes + small demo | K189: Yesterday: pgvector | L189: Notes + Anki | M189: 3
A190: 189 | B190: 46460 | C190: 27 | D190: Phase 5 - Embeddings & RAG | E190: WEEKLY CHECKPOINT 27: Embeddings & vector search | F190: Whole week | G190: Anki + notes (30 min) | H190: OWN | I190: - | J190: Self-test 10 concept Qs + interview Qs: HNSW vs IVF-PQ; Why normalise; When pgvector is enough (score bands: <40 weak, 40-60 needs work, 60-75 acceptable, 75-90 strong, 90+ excellent; <75% => revise before next week) (60 min); redo hardest implementation from blank file (30 min) | K190: Whole week | L190: Score + 200-word weekly note + push | M190: 3
A191: 190 | B191: 46461 | C191: 28 | D191: Phase 5 - Embeddings & RAG | E191: Ingestion | F191: PDF/tables; metadata | G191: OWN (pypdf docs) | H191: OWN | I191: - | J191: Ingestion for SEBI/RBI docs | K191: Yesterday: Late interaction (concept) | L191: Commit | M191: 3
A192: 191 | B192: 46462 | C192: 28 | D192: Phase 5 - Embeddings & RAG | E192: Chunking | F192: Fixed/recursive/semantic/structure | G192: CONTEXTUAL (chunking part) | H192: CONTEXTUAL | I192: https://www.anthropic.com/news/contextual-retrieval | J192: 3 chunkers | K192: Yesterday: Ingestion | L192: Commit | M192: 3
A193: 192 | B193: 46463 | C193: 28 | D193: Phase 5 - Embeddings & RAG | E193: BM25 from scratch | F193: TF-IDF, BM25, k1/b | G193: BM25 sec 1-3 | H193: BM25 | I193: https://www.staff.city.ac.uk/~sbrp622/papers/foundations_bm25_review.pdf | J193: BM25 index; compare rank_bm25 | K193: Yesterday: Chunking | L193: Commit + tests | M193: 3
A194: 193 | B194: 46464 | C194: 28 | D194: Phase 5 - Embeddings & RAG | E194: Hybrid & RRF | F194: Fusion; metadata filters | G194: Project/build day - no new reading | H194: OWN | I194: - | J194: Hybrid retrieval | K194: Yesterday: BM25 from scratch | L194: Commit | M194: 3
A195: 194 | B195: 46465 | C195: 28 | D195: Phase 5 - Embeddings & RAG | E195: Reranking | F195: Cross-encoders; latency | G195: LIN ch 3 | H195: LIN | I195: https://arxiv.org/abs/2010.06467 | J195: Cross-encoder reranker; latency table | K195: Yesterday: Hybrid & RRF | L195: Commit | M195: 3
... A224: 223 | B224: 46494 | C224: 32 | D224: Phase 5 - Embeddings & RAG | E224: P4 defence | F224: 9 questions + video | G224: Project/build day - no new reading | H224: OWN | I224: - | J224: Answers + video | K224: Yesterday: P4 system design | L224: CP4 self-grade | M224: 5
A225: 224 | B225: 46495 | C225: 32 | D225: Phase 5 - Embeddings & RAG | E225: WEEKLY CHECKPOINT 32: PROJECT 4 (week 2) | F225: Whole week | G225: Anki + notes (30 min) | H225: OWN | I225: - | J225: Self-test 10 concept Qs + interview Qs: Design RAG at 10M docs; Cost per query levers; V2 plan (score bands: <40 weak, 40-60 needs work, 60-75 acceptable, 75-90 strong, 90+ excellent; <75% => revise before next week) (60 min); redo hardest implementation from blank file (30 min) | K225: Whole week | L225: Score + 200-word weekly note + push | M225: 5 | N225: CP4
A226: 225 | B226: 46496 | C226: 33 | D226: Phase 6 - Fine-tuning | E226: Transfer learning & full FT | F226: Freezing; per-layer LR; forgetting | G226: HF-LLM ch 3 | H226: HF-LLM | I226: https://huggingface.co/learn/llm-course | J226: Full FT small model on classification | K226: Yesterday: P4 defence | L226: Commit | M226: 4
A227: 226 | B227: 46497 | C227: 33 | D227: Phase 6 - Fine-tuning | E227: LoRA math | F227: Low-rank update; rank/alpha; targets | G227: LORA sec 4 | H227: LORA | I227: https://arxiv.org/abs/2106.09685 | J227: LoRA layer from scratch; verify vs PEFT | K227: Yesterday: Transfer learning & full FT | L227: Commit + tests | M227: 4
A228: 227 | B228: 46498 | C228: 33 | D228: Phase 6 - Fine-tuning | E228: Quantisation basics | F228: INT8/INT4, NF4, dequant | G228: QLORA sec 3 | H228: QLORA | I228: https://arxiv.org/abs/2305.14314 | J228: Quantise weights from scratch (INT8, NF4 sim) | K228: Yesterday: LoRA math | L228: Commit | M228: 4
A229: 228 | B229: 46499 | C229: 33 | D229: Phase 6 - Fine-tuning | E229: QLoRA in practice | F229: 4-bit base; paged optimisers; 6 GB | G229: UNSLOTH guide | H229: UNSLOTH | I229: https://docs.unsloth.ai/ | J229: QLoRA 1-3B on 3060 | K229: Yesterday: Quantisation basics | L229: Run + eval | M229: 4
A230: 229 | B230: 46500 | C230: 33 | D230: Phase 6 - Fine-tuning | E230: PEFT landscape | F230: Adapters, prompt tuning, DoRA | G230: PEFT conceptual guides | H230: PEFT | I230: https://huggingface.co/docs/peft | J230: Quick LoRA vs DoRA | K230: Yesterday: QLoRA in practice | L230: Notes | M230: 4
A231: 230 | B231: 46501 | C231: 33 | D231: Phase 6 - Fine-tuning | E231: Fine-tune evaluation | F231: Held-out eval; judge; regression tests | G231: Project/build day - no new reading | H231: OWN | I231: - | J231: Eval harness | K231: Yesterday: PEFT landscape | L231: `ft/eval.py` + Anki | M231: 4
A232: 231 | B232: 46502 | C232: 33 | D232: Phase 6 - Fine-tuning | E232: WEEKLY CHECKPOINT 33: PEFT & quantisation | F232: Whole week | G232: Anki + notes (30 min) | H232: OWN | I232: - | J232: Self-test 10 concept Qs + interview Qs: LoRA rank intuition; NF4 vs INT4; Why QLoRA fits 6 GB (score bands: <40 weak, 40-60 needs work, 60-75 acceptable, 75-90 strong, 90+ excellent; <75% => revise before next week) (60 min); redo hardest implementation from blank file (30 min) | K232: Whole week | L232: Score + 200-word weekly note + push | M232: 4
A233: 232 | B233: 46503 | C233: 34 | D233: Phase 6 - Fine-tuning | E233: Dataset prep | F233: Formats; filtering; dedup; synthetic caveats | G233: HUYEN ch 8 (data) skim | H233: OWN | I233: - | J233: 500-example domain instruction set | K233: Yesterday: Fine-tune evaluation | L233: Dataset | M233: 4
A234: 233 | B234: 46504 | C234: 34 | D234: Phase 6 - Fine-tuning | E234: SFT | F234: Loss masking; packing | G234: RASCHKA ch 7; TRL SFTTrainer | H234: TRL | I234: https://huggingface.co/docs/trl | J234: SFT with TRL + masking check | K234: Yesterday: Dataset prep | L234: Eval | M234: 4
A235: 234 | B235: 46505 | C235: 34 | D235: Phase 6 - Fine-tuning | E235: DPO | F235: Pairs; beta; reference | G235: DPO paper; TRL DPOTrainer | H235: TRL | I235: https://huggingface.co/docs/trl | J235: DPO on 200 pairs | K235: Yesterday: SFT | L235: Eval | M235: 4
A236: 235 | B236: 46506 | C236: 34 | D236: Phase 6 - Fine-tuning | E236: Catastrophic forgetting | F236: Measure; replay; LoRA mitigation | G236: Project/build day - no new reading | H236: OWN | I236: - | J236: Measure on general eval; mitigate | K236: Yesterday: DPO | L236: Report | M236: 4
A237: 236 | B237: 46507 | C237: 34 | D237: Phase 6 - Fine-tuning | E237: RAG vs fine-tuning | F237: Knowledge vs behaviour; freshness; cost | G237: HUYEN ch 7 | H237: HUYEN | I237: https://www.oreilly.com/library/view/ai-engineering/9781098166298/ | J237: Decision matrix; 5 cases | K237: Yesterday: Catastrophic forgetting | L237: `decision.md` | M237: 4
... A280: 279 | B280: 46550 | C280: 40 | D280: Phase 7 - Agents | E280: P5 defence + demo | F280: 9 questions; video | G280: Project/build day - no new reading | H280: OWN | I280: - | J280: Answers + video | K280: Yesterday: P5 reproduce | L280: CP5 self-grade | M280: 4
A281: 280 | B281: 46551 | C281: 40 | D281: Phase 7 - Agents | E281: WEEKLY CHECKPOINT 40: PROJECT 5 (week 2) | F281: Whole week | G281: Anki + notes (30 min) | H281: OWN | I281: - | J281: Self-test 10 concept Qs + interview Qs: Where voice latency goes; Code-switch handling; V2 plan (score bands: <40 weak, 40-60 needs work, 60-75 acceptable, 75-90 strong, 90+ excellent; <75% => revise before next week) (60 min); redo hardest implementation from blank file (30 min) | K281: Whole week | L281: Score + 200-word weekly note + push | M281: 4 | N281: CP5
A282: 281 | B282: 46552 | C282: 41 | D282: Phase 8 - Speech internals & edge | E282: Audio features | F282: STFT, mel, MFCC | G282: HF-AUDIO unit 1 | H282: HF-AUDIO | I282: https://huggingface.co/learn/audio-course | J282: Mel extractor from scratch | K282: Yesterday: P5 defence + demo | L282: Commit + tests | M282: 4
A283: 282 | B283: 46553 | C283: 41 | D283: Phase 8 - Speech internals & edge | E283: CTC | F283: Alignment-free loss; decoding | G283: CTC (Distill) | H283: CTC | I283: https://distill.pub/2017/ctc/ | J283: CTC forward (NumPy); greedy + beam decode | K283: Yesterday: Audio features | L283: Commit + tests | M283: 4
A284: 283 | B284: 46554 | C284: 41 | D284: Phase 8 - Speech internals & edge | E284: Self-supervised speech | F284: wav2vec 2.0; Conformer | G284: WAV2VEC sec 2-3; CONFORMER sec 2 | H284: WAV2VEC | I284: https://arxiv.org/abs/2006.11477 | J284: Fine-tune wav2vec2 head on Tamil subset | K284: Yesterday: CTC | L284: WER | M284: 4
A285: 284 | B285: 46555 | C285: 41 | D285: Phase 8 - Speech internals & edge | E285: Streaming ASR | F285: VAD; endpointing; chunking | G285: SILERO; FWHISPER | H285: SILERO | I285: https://github.com/snakers4/silero-vad | J285: Streaming STT service | K285: Yesterday: Self-supervised speech | L285: Latency table | M285: 4
A286: 285 | B286: 46556 | C286: 41 | D286: Phase 8 - Speech internals & edge | E286: Audio embeddings & CLIP | F286: CLAP/wav2vec embeddings; CLIP loss | G286: CLIP sec 2-3 | H286: CLIP | I286: https://arxiv.org/abs/2103.00020 | J286: Audio similarity with your HNSW; CLIP zero-shot | K286: Yesterday: Streaming ASR | L286: Commit | M286: 4
A287: 286 | B287: 46557 | C287: 41 | D287: Phase 8 - Speech internals & edge | E287: Vision-language models | F287: Projector; usage; limits | G287: LLAVA sec 3 | H287: LLAVA | I287: https://arxiv.org/abs/2304.08485 | J287: VLM over machine photos | K287: Yesterday: Audio embeddings & CLIP | L287: Commit + Anki | M287: 4
A288: 287 | B288: 46558 | C288: 41 | D288: Phase 8 - Speech internals & edge | E288: WEEKLY CHECKPOINT 41: ASR internals + TTS + VLM | F288: Whole week | G288: Anki + notes (30 min) | H288: OWN | I288: - | J288: Self-test 10 concept Qs + interview Qs: CTC blank; Streaming latency parts; CLIP loss (score bands: <40 weak, 40-60 needs work, 60-75 acceptable, 75-90 strong, 90+ excellent; <75% => revise before next week) (60 min); redo hardest implementation from blank file (30 min) | K288: Whole week | L288: Score + 200-word weekly note + push | M288: 4
A289: 288 | B289: 46559 | C289: 42 | D289: Phase 8 - Speech internals & edge | E289: ONNX deep dive | F289: Graph, opsets, EPs | G289: ONNX docs | H289: ONNX | I289: https://onnxruntime.ai/docs/ | J289: Export Whisper-tiny + CNN; parity | K289: Yesterday: Vision-language models | L289: Commit | M289: 4
...

Sheet Sources
A1: Key | B1: Resource | C1: URL | D1: What to study | E1: What to skip
A2: MML | B2: Mathematics for Machine Learning (Deisenroth, Faisal, Ong) - free PDF | C2: https://mml-book.github.io/ | D2: Ch 2-8, 10 | E2: Ch 9, 11, 12
A3: 3B1B-LA | B3: 3Blue1Brown - Essence of Linear Algebra | C3: https://www.3blue1brown.com/topics/linear-algebra | D3: All 16 episodes | E3: -
A4: 3B1B-CALC | B4: 3Blue1Brown - Essence of Calculus | C4: https://www.3blue1brown.com/topics/calculus | D4: Ep 1-4, 6 | E4: -
A5: BRUCE | B5: Practical Statistics for Data Scientists (Bruce & Bruce, O'Reilly) | C5: https://www.oreilly.com/library/view/practical-statistics-for/9781492072935/ | D5: Ch 1-3 | E5: Ch 4-7
A6: NG | B6: Andrew Ng - Machine Learning Specialization (Coursera, audit free) | C6: https://www.coursera.org/specializations/machine-learning-introduction | D6: C1-C3 lectures; implement labs in NumPy/PyTorch | E6: TensorFlow labs
A7: GERON | B7: Hands-On Machine Learning, 3rd ed. (Géron) | C7: https://github.com/ageron/handson-ml3 | D7: Ch 2-9 | E7: Ch 10+ (Keras)
A8: SHAP | B8: SHAP documentation | C8: https://shap.readthedocs.io/ | D8: Intro + TreeExplainer | E8: Everything else
A9: LGBM | B9: LightGBM parameters docs | C9: https://lightgbm.readthedocs.io/en/latest/Parameters-Tuning.html | D9: Tuning page | E9: -
A10: KAGGLE-FE | B10: Kaggle Learn - Feature Engineering | C10: https://www.kaggle.com/learn/feature-engineering | D10: All | E10: -
A11: OPTUNA | B11: Optuna docs | C11: https://optuna.readthedocs.io/ | D11: Tutorial | E11: -
A12: IMBL | B12: imbalanced-learn user guide | C12: https://imbalanced-learn.org/stable/user_guide.html | D12: Over/under-sampling caveats | E12: -
... A108: OUTLINES | B108: Outlines (structured generation) | C108: https://github.com/dottxt-ai/outlines | D108: README | E108: -
